dbsa/__init__.py
dbsa/hive.py
dbsa/markdown.py
dbsa/presto.py
dbsa/redshift.py
dbsa/trino.py
dbsa/trino_iceberg.py
dbsa-0.1.1.dist-info/licenses/LICENSE
dbsa-0.1.1.dist-info/METADATA
dbsa-0.1.1.dist-info/WHEEL
dbsa-0.1.1.dist-info/entry_points.txt
dbsa-0.1.1.dist-info/top_level.txt
dbsa-0.1.1.dist-info/RECORD
