Metadata-Version: 2.4
Name: dbsa
Version: 0.1.1
Summary: Database schema definitions
Home-page: https://github.com/dataleio/dbsa
Author: Bence Faludi
Author-email: bence@subninja.org
License: MIT
License-File: LICENSE
Requires-Dist: jinja2
Dynamic: author
Dynamic: author-email
Dynamic: home-page
Dynamic: license
Dynamic: license-file
Dynamic: requires-dist
Dynamic: summary
